odoo/addons/l10n_es_cooperator/README.rst
odoo/addons/l10n_es_cooperator/__init__.py
odoo/addons/l10n_es_cooperator/__manifest__.py
odoo/addons/l10n_es_cooperator/i18n/l10n_es_cooperator.pot
odoo/addons/l10n_es_cooperator/models/__init__.py
odoo/addons/l10n_es_cooperator/models/subscription_request.py
odoo/addons/l10n_es_cooperator/readme/CONTRIBUTORS.rst
odoo/addons/l10n_es_cooperator/readme/DESCRIPTION.rst
odoo/addons/l10n_es_cooperator/readme/ROADMAP.rst
odoo/addons/l10n_es_cooperator/static/description/icon.png
odoo/addons/l10n_es_cooperator/static/description/index.html
odoo/addons/l10n_es_cooperator/views/subscription_request_view.xml
odoo/addons/l10n_es_cooperator/views/subscription_templates.xml
odoo12_addon_l10n_es_cooperator-12.0.0.1.1.dist-info/METADATA
odoo12_addon_l10n_es_cooperator-12.0.0.1.1.dist-info/WHEEL
odoo12_addon_l10n_es_cooperator-12.0.0.1.1.dist-info/top_level.txt
odoo12_addon_l10n_es_cooperator-12.0.0.1.1.dist-info/RECORD
